{
    "video_id": "T7GwBRmsb5k",
    "channel_id": "UCButXdOd8lK7w3ezYUd7vew",
    "title": "Can we bot it ? Three mages account with one Xbox controller (Diablo 4)",
    "description": "Just a video showing a bit the advancement of the tool XOMI to control Xbox with UDP message.",
    "keywords": "['diablo', 'bot', 'macro', 'tool', 'xbox', 'controller', 'forfun']",
    "author": "OMI: Can we bot it ?",
    "push_date": "2023-06-19 00:00:00",
    "thumbnail_url": "https://i.ytimg.com/vi/T7GwBRmsb5k/sddefault.jpg?sqp=-oaymwEmCIAFEOAD8quKqQMa8AEB-AH-CYAC0AWKAgwIABABGGUgUChBMA8=&rs=AOn4CLCfKAy3t-h4NgEVLHnkUsoThn3qhA"
}