{
    "video_id": "s2drhv-jPUg",
    "channel_id": "UComxuwj8ulaREOdtNwwhI-w",
    "title": "Stereo Visit of the Metro #ZedMini #WMR",
    "description": "Use Gear VR, Oculus Go or Cardboard youtube app to see the result.\nFeel free to ask any questions in comment, or here:\nhttp://www.patreon.com/eloistree",
    "keywords": "[]",
    "author": "\u00c9loi Str\u00e9e, \uab32\ud83e\uddf0: Raw video",
    "push_date": "2018-07-12 00:00:00",
    "thumbnail_url": "https://i.ytimg.com/vi/s2drhv-jPUg/sddefault.jpg"
}