{
    "video_id": "FMGnUi34u6Y",
    "channel_id": "UCh31PSAE2YS0QOlobn-ix6Q",
    "title": "Guide of Lynx R1: Lynx Demo Manager and surrounding",
    "description": "Video to start a bit on the Lynx and to understand what is around the Lynx Manager. Download manager: https://portal.lynx-r.com/downloads/",
    "keywords": "['XR', 'ADB', 'Lynx', 'Manager', 'Guide', 'Tutorial', 'Beginner', 'Scrcpy', 'install', 'APK', 'Screen', 'Debug']",
    "author": "Learn By Playing In XR",
    "push_date": "2023-11-03 00:00:00",
    "thumbnail_url": "https://i.ytimg.com/vi/FMGnUi34u6Y/sddefault.jpg?sqp=-oaymwEmCIAFEOAD8quKqQMa8AEB-AH-CYAC0AWKAgwIABABGH8gLigTMA8=&rs=AOn4CLDqJL7WtjV_sLsd6XAeG6BI7mMRdA"
}